cryptcrro-0.1.5.dist-info/METADATA
cryptcrro-0.1.5.dist-info/WHEEL
cryptcrro-0.1.5.dist-info/licenses/LICENSE
cryptcrro/aes256_ctr.py
cryptcrro/arith.py
cryptcrro/asymetric.py
cryptcrro/chacha20.py
cryptcrro/ecdsa.py
cryptcrro/ecies.py
cryptcrro/hmac.py
cryptcrro/rsa.py
cryptcrro/secp256k1.py
cryptcrro/sha256_ctr.py
cryptcrro/symetric.py
cryptcrro/test.py
cryptcrro/utility.py
cryptcrro/__init__.py
cryptcrro/_rust.cp311-win_amd64.pyd
cryptcrro-0.1.5.dist-info/RECORD
