Metadata-Version: 2.4
Name: cryptcrro
Version: 0.1.5
Classifier: Programming Language :: Python
Classifier: Programming Language :: Rust
License-File: LICENSE
Summary: A cryptography librairy
Author-email: The Crro Project <elgremonter@gmail.com>
License: MIT
